py_type/__init__.py
py_type/annotations.py
py_type/checks.py
py_type/output.py
py_type-0.0.5.dist-info/DESCRIPTION.rst
py_type-0.0.5.dist-info/METADATA
py_type-0.0.5.dist-info/RECORD
py_type-0.0.5.dist-info/WHEEL
py_type-0.0.5.dist-info/metadata.json
py_type-0.0.5.dist-info/top_level.txt
