Metadata-Version: 2.0
Name: py-type
Version: 0.0.5
Summary: A simple library for dynamic type checking in Python
Home-page: https://github.com/aberkley/py_type
Author: Alexander Berkley
Author-email: alexander.berkley@gmail.com
License: MIT
Keywords: python typing
Platform: UNKNOWN
Classifier: Development Status :: 3 - Alpha
Classifier: Topic :: Utilities
Classifier: License :: OSI Approved :: BSD License
Requires-Dist: pandas (==0.19.2)
